{
  "EdsAnimFadeQuick": "0.15s",
  "EdsAnimFadeLong": "0.4s",
  "EdsAnimMoveQuick": "0.15s",
  "EdsAnimMoveLong": "0.4s",
  "EdsAnimEase": "ease",
  "EdsBorderWidthSm": "1px",
  "EdsBorderWidthMd": "2px",
  "EdsBorderWidthLg": "4px",
  "EdsBorderWidthXl": "8px",
  "EdsBorderRadiusMd": "4px",
  "EdsBorderRadiusLg": "8px",
  "EdsBorderRadiusXl": "20px",
  "EdsBorderRadiusRound": "50%",
  "EdsColorBrandGrape100": "#F0F0FC",
  "EdsColorBrandGrape200": "#E0E0F9",
  "EdsColorBrandGrape300": "#C4C1F3",
  "EdsColorBrandGrape400": "#A6A3EE",
  "EdsColorBrandGrape500": "#8984E8",
  "EdsColorBrandGrape600": "#6B65E2",
  "EdsColorBrandGrape700": "#5751D2",
  "EdsColorBrandGrape800": "#3E42B1",
  "EdsColorNeutral100": "#F5F6F8",
  "EdsColorNeutral200": "#E7E8EA",
  "EdsColorNeutral300": "#C0C4C8",
  "EdsColorNeutral400": "#A2A3A8",
  "EdsColorNeutral500": "#878C90",
  "EdsColorNeutral600": "#707070",
  "EdsColorNeutral700": "#505058",
  "EdsColorNeutral800": "#21272D",
  "EdsColorNeutralWhite": "#ffffff",
  "EdsColorNeutralBlack": "#161B1F",
  "EdsColorTransparent25": "rgba(0, 0, 0, .25)",
  "EdsColorTransparent90": "rgba(0, 0, 0, .9)",
  "EdsColorOtherMint100": "#ECFFF5",
  "EdsColorOtherMint200": "#B7E9CE",
  "EdsColorOtherMint300": "#8FDCB3",
  "EdsColorOtherMint400": "#59C88C ",
  "EdsColorOtherMint500": "#00A56A",
  "EdsColorOtherMint600": "#008656",
  "EdsColorOtherMint700": "#007249",
  "EdsColorOtherMint800": "#005939",
  "EdsColorOtherYellow100": "#FFF1E9",
  "EdsColorOtherYellow400": "#F7BE2D",
  "EdsColorOtherLemon": "#F5FF8F",
  "EdsColorOtherOrange100": "#FFF1E9",
  "EdsColorOtherOrange200": "#FFCBA5",
  "EdsColorOtherOrange300": "#FFAF76",
  "EdsColorOtherOrange400": "#F6924A",
  "EdsColorOtherOrange500": "#E06B00",
  "EdsColorOtherOrange600": "#C64600",
  "EdsColorOtherOrange700": "#AC3400",
  "EdsColorOtherOrange800": "#842800",
  "EdsColorOtherRuby100": "#FFF0F4",
  "EdsColorOtherRuby200": "#FFCBD7",
  "EdsColorOtherRuby300": "#FB90B0",
  "EdsColorOtherRuby400": "#F76C96",
  "EdsColorOtherRuby500": "#F1497B",
  "EdsColorOtherRuby600": "#D41E52",
  "EdsColorOtherRuby700": "#BD0044",
  "EdsColorOtherRuby800": "#8F0134",
  "EdsLMaxWidth": "71.25rem",
  "EdsLSidebarWidth": "13.5rem",
  "EdsLLinelengthWidth": "36rem",
  "EdsBoxShadowSm": "0px 1px 2px 1px rgba(0, 0, 0, 0.2)",
  "EdsBoxShadowMd": "0px 0px 0px 1px var(--eds-color-neutral-200), 0px 2px 3px rgba(0, 0, 0, 0.02), 0px 4px 8px rgba(0, 0, 0, 0.08)",
  "EdsSize1": "0.5rem",
  "EdsSize2": "1rem",
  "EdsSize3": "1.5rem",
  "EdsSize4": "2rem",
  "EdsSize5": "2.5rem",
  "EdsSize6": "3rem",
  "EdsSize7": "3.5rem",
  "EdsSize8": "4rem",
  "EdsSize9": "4.5rem",
  "EdsSize10": "5rem",
  "EdsSizeBaseUnit": "0.5rem",
  "EdsSizeHalf": "0.25rem",
  "EdsSize1AndHalf": "0.75rem",
  "EdsSize2AndHalf": "1.25rem",
  "EdsFontFamilyPrimary": "'Open Sans', sans-serif",
  "EdsFontFamilySecondary": "'Open Sans', sans-serif",
  "EdsFontSize11": "0.688rem",
  "EdsFontSize12": "0.75rem",
  "EdsFontSize14": "0.875rem",
  "EdsFontSize16": "1rem",
  "EdsFontSize18": "1.125rem",
  "EdsFontSize24": "1.5rem",
  "EdsFontSize32": "2rem",
  "EdsFontSize40": "2.5rem",
  "EdsFontWeightLight": "400",
  "EdsFontWeightMedium": "500",
  "EdsFontWeightBold": "600",
  "EdsLetterSpacingSm": "0.5px",
  "EdsZIndex0": "0",
  "EdsZIndex100": "100",
  "EdsZIndex200": "200",
  "EdsZIndex300": "300",
  "EdsZIndex400": "400",
  "EdsZIndex500": "500",
  "EdsZIndexTop": "99999",
  "EdsZIndexBottom": "-100",
  "EdsThemeBorderRadius": "4px",
  "EdsThemeBorderWidth": "1px",
  "EdsThemeColorBackgroundNeutralDefault": "#ffffff",
  "EdsThemeColorBackgroundNeutralDefaultHover": "#F5F6F8",
  "EdsThemeColorBackgroundNeutralMedium": "#E7E8EA",
  "EdsThemeColorBackgroundNeutralMediumHover": "#C0C4C8",
  "EdsThemeColorBackgroundNeutralSubtle": "#F5F6F8",
  "EdsThemeColorBackgroundNeutralSubtleHover": "#E7E8EA",
  "EdsThemeColorBackgroundBrandPrimaryDefault": "#F0F0FC",
  "EdsThemeColorBackgroundBrandPrimaryStrong": "#5751D2",
  "EdsThemeColorBackgroundUtilitySuccess": "#ECFFF5",
  "EdsThemeColorBackgroundUtilityWarning": "#FFF1E9",
  "EdsThemeColorBackgroundUtilityError": "#FFF0F4",
  "EdsThemeColorBackgroundGradeCompleteDefault": "#008656",
  "EdsThemeColorBackgroundGradeCompleteSubtle": "#ECFFF5",
  "EdsThemeColorBackgroundGradeReviseDefault": "#F7BE2D",
  "EdsThemeColorBackgroundGradeReviseSubtle": "#FFF1E9",
  "EdsThemeColorBackgroundGradeStopDefault": "#D41E52",
  "EdsThemeColorBackgroundGradeStopSubtle": "#FFF0F4",
  "EdsThemeColorBackgroundDisabled": "#C0C4C8",
  "EdsThemeColorBorderNeutralDefault": "#C0C4C8",
  "EdsThemeColorBorderNeutralDefaultHover": "#A2A3A8",
  "EdsThemeColorBorderNeutralStrong": "#878C90",
  "EdsThemeColorBorderNeutralStrongHover": "#707070",
  "EdsThemeColorBorderNeutralSubtle": "#E7E8EA",
  "EdsThemeColorBorderNeutralSubtleHover": "#C0C4C8",
  "EdsThemeColorBorderBrandPrimary": "#C4C1F3",
  "EdsThemeColorBorderBrandPrimaryHover": "#A6A3EE",
  "EdsThemeColorBorderUtilitySuccessDefault": "#8FDCB3",
  "EdsThemeColorBorderUtilitySuccessStrong": "#00A56A",
  "EdsThemeColorBorderUtilityWarningDefault": "#FFAF76",
  "EdsThemeColorBorderUtilityWarningStrong": "#E06B00",
  "EdsThemeColorBorderUtilityErrorDefault": "#FB90B0",
  "EdsThemeColorBorderUtilityErrorStrong": "#F1497B",
  "EdsThemeColorBorderGradeComplete": "#8FDCB3",
  "EdsThemeColorBorderGradeRevise": "#FFF1E9",
  "EdsThemeColorBorderGradeStop": "#FB90B0",
  "EdsThemeColorBorderDisabled": "#C0C4C8",
  "EdsThemeColorIconNeutralDefault": "#707070",
  "EdsThemeColorIconNeutralDefaultKnockout": "#ffffff",
  "EdsThemeColorIconNeutralStrong": "#505058",
  "EdsThemeColorIconNeutralSubtle": "#878C90",
  "EdsThemeColorIconLinkDefault": "#8984E8",
  "EdsThemeColorIconLinkDefaultHover": "#6B65E2",
  "EdsThemeColorIconLinkStrong": "#8984E8",
  "EdsThemeColorIconLinkStrongHover": "#6B65E2",
  "EdsThemeColorIconBrandPrimary": "#8984E8",
  "EdsThemeColorIconBrandPrimaryHover": "#6B65E2",
  "EdsThemeColorIconUtilitySuccess": "#00A56A",
  "EdsThemeColorIconUtilitySuccessHover": "#008656",
  "EdsThemeColorIconUtilityWarning": "#E06B00",
  "EdsThemeColorIconUtilityWarningHover": "#C64600",
  "EdsThemeColorIconUtilityError": "#F1497B",
  "EdsThemeColorIconUtilityErrorHover": "#D41E52",
  "EdsThemeColorIconGradeComplete": "#00A56A",
  "EdsThemeColorIconGradeCompleteHover": "#00A56A",
  "EdsThemeColorIconGradeRevise": "#21272D",
  "EdsThemeColorIconGradeReviseHover": "#161B1F",
  "EdsThemeColorIconGradeStop": "#F1497B",
  "EdsThemeColorIconGradeStopHover": "#F1497B",
  "EdsThemeColorIconDisabled": "#C0C4C8",
  "EdsThemeColorTextNeutralDefault": "#505058",
  "EdsThemeColorTextNeutralDefaultKnockout": "#ffffff",
  "EdsThemeColorTextNeutralStrong": "#21272D",
  "EdsThemeColorTextNeutralSubtle": "#707070",
  "EdsThemeColorTextLinkDefault": "#21272D",
  "EdsThemeColorTextLinkDefaultHover": "#161B1F",
  "EdsThemeColorTextLinkStrong": "#5751D2",
  "EdsThemeColorTextLinkStrongHover": "#3E42B1",
  "EdsThemeColorTextUtilitySuccess": "#007249",
  "EdsThemeColorTextUtilityWarning": "#AC3400",
  "EdsThemeColorTextUtilityError": "#BD0044",
  "EdsThemeColorTextGradeComplete": "#007249",
  "EdsThemeColorTextGradeRevise": "#21272D",
  "EdsThemeColorTextGradeStop": "#BD0044",
  "EdsThemeColorTextDisabled": "#C0C4C8",
  "EdsThemeColorBodyBackground": "#F5F6F8",
  "EdsThemeColorBodyBackgroundInverted": "#505058",
  "EdsThemeColorFocusRing": "#6B65E2",
  "EdsThemeColorFocusRingInverted": "#ffffff",
  "EdsThemeColorFormLabelText": "#505058",
  "EdsThemeColorFormLabelTextInverted": "#ffffff",
  "EdsThemeColorFormInputBorder": "#C0C4C8",
  "EdsThemeColorFormInputBorderHover": "#A2A3A8",
  "EdsThemeColorFormInputBorderInverted": "#ffffff",
  "EdsThemeColorFormInputBorderInvertedHover": "#ffffff",
  "EdsThemeColorFormInputBorderFocus": "#878C90",
  "EdsThemeColorFormInputBorderFocusInverted": "#ffffff",
  "EdsThemeColorFormInputBorderError": "#F1497B",
  "EdsThemeColorTextHighlightForeground": "#21272D",
  "EdsThemeColorTextHighlightBackground": "#F5FF8F",
  "EdsThemeBoxShadow": "0px 0px 0px 1px var(--eds-color-neutral-200), 0px 2px 3px rgba(0, 0, 0, 0.02), 0px 4px 8px rgba(0, 0, 0, 0.08)",
  "EdsThemeFormInputBorderWidth": "1px",
  "EdsThemeFormInputBorderRadius": "4px"
}